platechain/__init__.py
platechain/chain.py
platechain/constants.py
platechain/prompts.py
platechain/utils.py
platechain-0.0.5.dist-info/LICENSE
platechain-0.0.5.dist-info/METADATA
platechain-0.0.5.dist-info/WHEEL
platechain-0.0.5.dist-info/RECORD
